{
  "objectInfo" : {
    "id" : "4U49ZAyyKAgcTDqqIbWhaY",
    "name" : "mtt_Techm_Mapplet",
    "type" : "MTT",
    "metadata" : {
      "modelVersion" : {
        "major" : 0,
        "minor" : 0
      },
      "repoInfo" : {
        "repoHandle" : "010TYA0Z00000000000A"
      },
      "contextAttributes" : [ {
        "name" : "id",
        "value" : "@1"
      } ],
      "additionalInfo" : {
        "description" : "",
        "contentType" : "JSON",
        "documentState" : "VALID"
      }
    }
  },
  "dataFileExtension" : "zip",
  "updateTime" : "2024-02-09T05:26:24.222Z",
  "objectRefs" : [ {
    "id" : "6Hn3BgGSQaAeUVTDfka0eJ",
    "name" : "DEV_FF_SRC",
    "type" : "Connection",
    "metadata" : {
      "modelVersion" : {
        "major" : 0,
        "minor" : 0
      },
      "repoInfo" : {
        "repoHandle" : "010TYA0B000000000002"
      },
      "contextAttributes" : null,
      "additionalInfo" : {
        "description" : null,
        "contentType" : "JSON",
        "documentState" : "COMPLETE"
      }
    },
    "path" : "/SYS"
  }, {
    "id" : "0pyEb27g1mNbbTzQJByCUS",
    "name" : "DEV_ORCL_HR",
    "type" : "Connection",
    "metadata" : {
      "modelVersion" : {
        "major" : 0,
        "minor" : 0
      },
      "repoInfo" : {
        "repoHandle" : "010TYA0B000000000004"
      },
      "contextAttributes" : null,
      "additionalInfo" : {
        "description" : null,
        "contentType" : "JSON",
        "documentState" : "COMPLETE"
      }
    },
    "path" : "/SYS"
  }, {
    "id" : "7iuE1M1dOtXgRRrYXNfjSQ",
    "name" : "m_TECHM_Mapplet_Demo",
    "type" : "DTEMPLATE",
    "metadata" : {
      "modelVersion" : {
        "major" : 0,
        "minor" : 0
      },
      "repoInfo" : {
        "repoHandle" : "010TYA1700000000000H"
      },
      "contextAttributes" : [ {
        "name" : "id",
        "value" : "@1"
      } ],
      "additionalInfo" : {
        "description" : "",
        "contentType" : "JSON",
        "documentState" : "VALID"
      }
    },
    "path" : "/Explore/TECHM_TRAINING_IDMC/DEMO"
  }, {
    "id" : "6XwXlCoJ56MkyHR1FyLIMO",
    "name" : "DEV-WIN-AGENT",
    "type" : "AgentGroup",
    "metadata" : {
      "modelVersion" : {
        "major" : 0,
        "minor" : 0
      },
      "repoInfo" : {
        "repoHandle" : "010TYA25000000000002"
      },
      "contextAttributes" : null,
      "additionalInfo" : {
        "description" : null,
        "contentType" : "JSON",
        "documentState" : "VALID"
      }
    },
    "path" : "/SYS"
  }, {
    "id" : "8vR5WYIGyKblFkMuGjLKmW",
    "name" : "DEV_FF_TGT",
    "type" : "Connection",
    "metadata" : {
      "modelVersion" : {
        "major" : 0,
        "minor" : 0
      },
      "repoInfo" : {
        "repoHandle" : "010TYA0B000000000003"
      },
      "contextAttributes" : null,
      "additionalInfo" : {
        "description" : null,
        "contentType" : "JSON",
        "documentState" : "COMPLETE"
      }
    },
    "path" : "/SYS"
  } ]
}